sif_parser/__init__.py
sif_parser/__main__.py
sif_parser/_sif_open.py
sif_parser/_version.py
sif_parser/cli.py
sif_parser/plugin.py
sif_parser/sif_open.py
sif_parser/utils.py
sif_reader/__init__.py
sif_reader/__main__.py
sif_reader/_sif_open.py
sif_reader/_version.py
sif_reader/cli.py
sif_reader/plugin.py
sif_reader/sif_open.py
sif_reader/utils.py
sif_parser-0.3.0.dist-info/LICENSE
sif_parser-0.3.0.dist-info/METADATA
sif_parser-0.3.0.dist-info/WHEEL
sif_parser-0.3.0.dist-info/entry_points.txt
sif_parser-0.3.0.dist-info/top_level.txt
sif_parser-0.3.0.dist-info/RECORD
