Metadata-Version: 2.1
Name: sif-parser
Version: 0.3.0
Summary: Python package to read Andor sif file.
Home-page: https://github.com/fujiisoup/sif_parser
Author: Keisuke Fujii
Author-email: fujii@me.kyoto-u.ac.jp
License: BSD 3-clause
Keywords: imaging,Andor
Platform: UNKNOWN
Classifier: License :: OSI Approved :: BSD License
Classifier: Natural Language :: English
Classifier: Operating System :: MacOS :: MacOS X
Classifier: Operating System :: Microsoft :: Windows
Classifier: Operating System :: POSIX :: Linux
Classifier: Programming Language :: Python :: 3.6
Classifier: Topic :: Scientific/Engineering :: Physics
License-File: LICENSE
Requires-Dist: numpy (>=1.10)
Requires-Dist: pandas
